README.md
setup.py
vizsequence/__init__.py
vizsequence/viz_sequence.py
vizsequence.egg-info/PKG-INFO
vizsequence.egg-info/SOURCES.txt
vizsequence.egg-info/dependency_links.txt
vizsequence.egg-info/requires.txt
vizsequence.egg-info/top_level.txt