Metadata-Version: 1.0
Name: vizsequence
Version: 0.1.1.0
Summary: Utilities for visualizing dna sequences
Home-page: https://github.com/kundajelab/vizsequence
Author: UNKNOWN
Author-email: UNKNOWN
License: UNKNOWN
Platform: UNKNOWN
